[{"__symbolic":"module","version":3,"metadata":{"InfiniteScrollDirective":{"__symbolic":"class","decorators":[{"__symbolic":"call","expression":{"__symbolic":"reference","module":"@angular/core","name":"Directive"},"arguments":[{"selector":"[infinite-scroll]","host":{"(scroll)":"onScroll($event)","$quoted$":["(scroll)"]}}]}],"members":{"scrollTrigger":[{"__symbolic":"property","decorators":[{"__symbolic":"call","expression":{"__symbolic":"reference","module":"@angular/core","name":"Input"},"arguments":["scroll-distance"]}]}],"OnScrollMethod":[{"__symbolic":"property","decorators":[{"__symbolic":"call","expression":{"__symbolic":"reference","module":"@angular/core","name":"Output"}}]}],"__ctor__":[{"__symbolic":"constructor","parameters":[{"__symbolic":"reference","module":"@angular/core","name":"ElementRef"}]}],"onScroll":[{"__symbolic":"method"}]}}}},{"__symbolic":"module","version":1,"metadata":{"InfiniteScrollDirective":{"__symbolic":"class","decorators":[{"__symbolic":"call","expression":{"__symbolic":"reference","module":"@angular/core","name":"Directive"},"arguments":[{"selector":"[infinite-scroll]","host":{"(scroll)":"onScroll($event)"}}]}],"members":{"scrollTrigger":[{"__symbolic":"property","decorators":[{"__symbolic":"call","expression":{"__symbolic":"reference","module":"@angular/core","name":"Input"},"arguments":["scroll-distance"]}]}],"OnScrollMethod":[{"__symbolic":"property","decorators":[{"__symbolic":"call","expression":{"__symbolic":"reference","module":"@angular/core","name":"Output"}}]}],"__ctor__":[{"__symbolic":"constructor","parameters":[{"__symbolic":"reference","module":"@angular/core","name":"ElementRef"}]}],"onScroll":[{"__symbolic":"method"}]}}}}]